{"0": {"ORDER_ID": "7824261440", "ADDRESS_SEND": "USNS Little/FPO AE 24808", "ADDRESS_RECEIVE": "", "NUM_PACKAGE": 4, "TOTAL WEIGHT": 63, "TOTAL_PRICE": ""}, "1": {"ORDER_ID": "2679653424", "ADDRESS_SEND": "09635 Richard Summit Suite 247/West David, HI 47267", "ADDRESS_RECEIVE": "", "NUM_PACKAGE": 1, "TOTAL WEIGHT": 5, "TOTAL_PRICE": ""}, "2": {"ORDER_ID": "6758125051", "ADDRESS_SEND": "3853 Brittney Valleys Suite 118/Cortezberg, TX 00650", "ADDRESS_RECEIVE": "", "NUM_PACKAGE": 4, "TOTAL WEIGHT": 108, "TOTAL_PRICE": ""}, "3": {"ORDER_ID": "3982286389", "ADDRESS_SEND": "419 Erik Corner/Lake Kevin, RI 60746", "ADDRESS_RECEIVE": "", "NUM_PACKAGE": 3, "TOTAL WEIGHT": 31, "TOTAL_PRICE": ""}, "4": {"ORDER_ID": "8773727124", "ADDRESS_SEND": "99880 Jillian Springs Suite 523/East Kelly, SD 29892", "ADDRESS_RECEIVE": "", "NUM_PACKAGE": 3, "TOTAL WEIGHT": 123, "TOTAL_PRICE": ""}, "5": {"ORDER_ID": "0204946948", "ADDRESS_SEND": "5337 Denise Landing/West Karen, TN 70337", "ADDRESS_RECEIVE": "", "NUM_PACKAGE": 4, "TOTAL WEIGHT": 61, "TOTAL_PRICE": ""}, "6": {"ORDER_ID": "0855499315", "ADDRESS_SEND": "336 Adams Ferry Apt. 438/East Stevenshire, ID 02289", "ADDRESS_RECEIVE": "", "NUM_PACKAGE": 3, "TOTAL WEIGHT": 93, "TOTAL_PRICE": ""}, "7": {"ORDER_ID": "8402844239", "ADDRESS_SEND": "97198 Jeffery Station/Lorihaven, MO 06802", "ADDRESS_RECEIVE": "", "NUM_PACKAGE": 4, "TOTAL WEIGHT": 125, "TOTAL_PRICE": ""}, "8": {"ORDER_ID": "4981680467", "ADDRESS_SEND": "308 Kelly Station/Lake David, NM 53639", "ADDRESS_RECEIVE": "", "NUM_PACKAGE": 4, "TOTAL WEIGHT": 81, "TOTAL_PRICE": ""}, "9": {"ORDER_ID": "6270372260", "ADDRESS_SEND": "027 David Dale Suite 556/Port John, PA 35023", "ADDRESS_RECEIVE": "", "NUM_PACKAGE": 2, "TOTAL WEIGHT": 55, "TOTAL_PRICE": ""}, "10": {"ORDER_ID": "2443992930", "ADDRESS_SEND": "PSC 0734, Box 4138/APO AP 17067", "ADDRESS_RECEIVE": "", "NUM_PACKAGE": 1, "TOTAL WEIGHT": 13, "TOTAL_PRICE": ""}, "11": {"ORDER_ID": "0826466758", "ADDRESS_SEND": "9242 Lewis Pines/Gaineshaven, UT 02662", "ADDRESS_RECEIVE": "", "NUM_PACKAGE": 1, "TOTAL WEIGHT": 6, "TOTAL_PRICE": ""}, "12": {"ORDER_ID": "8750694613", "ADDRESS_SEND": "74923 Allen Keys/North Michael, CT 31020", "ADDRESS_RECEIVE": "", "NUM_PACKAGE": 2, "TOTAL WEIGHT": 15, "TOTAL_PRICE": ""}, "13": {"ORDER_ID": "0938808800", "ADDRESS_SEND": "222 Miller Shore Apt. 113/Andrewborough, SD 33141", "ADDRESS_RECEIVE": "", "NUM_PACKAGE": 4, "TOTAL WEIGHT": 77, "TOTAL_PRICE": ""}, "14": {"ORDER_ID": "7430380220", "ADDRESS_SEND": "611 Tara Spurs/Davidburgh, KY 64213", "ADDRESS_RECEIVE": "", "NUM_PACKAGE": 1, "TOTAL WEIGHT": 11, "TOTAL_PRICE": ""}}